sitemapcrawler/__init__.py
sitemapcrawler/crawler.py
sitemapcrawler/requirements.txt
sitemapcrawler/test.py
sitemapcrawler-0.0.1.dist-info/METADATA
sitemapcrawler-0.0.1.dist-info/WHEEL
sitemapcrawler-0.0.1.dist-info/RECORD
