Metadata-Version: 2.1
Name: sitemapcrawler
Version: 0.0.1
Summary: A simple sitemap crawler that acts as the backbone for other operations
Project-URL: Homepage, https://github.com/bmelton/sitemapcrawler
Project-URL: Bug Tracker, https://github.com/bmelton/sitemapcrawler/issues
Author-email: Barry Melton <barry@sureisfun.com>
Classifier: License :: OSI Approved :: MIT License
Classifier: Operating System :: OS Independent
Classifier: Programming Language :: Python :: 3
Requires-Python: >=3.7
